PySimpleProperties/Properties.py
PySimpleProperties/__init__.py
PySimpleProperties-0.2.0.dist-info/LICENSE
PySimpleProperties-0.2.0.dist-info/METADATA
PySimpleProperties-0.2.0.dist-info/WHEEL
PySimpleProperties-0.2.0.dist-info/top_level.txt
PySimpleProperties-0.2.0.dist-info/RECORD
