Metadata-Version: 2.1
Name: PySimpleProperties
Version: 0.2.0
Summary: A simple adaptation of java properties
Home-page: https://github.com/JariBou/PySimpleProperties
Author: JariBou (Tomé Bourdié)
Author-email: <bourdietome@gmail.com>
License: LICENSE
Keywords: python,properties,file manager
Platform: UNKNOWN
Classifier: Development Status :: 4 - Beta
Classifier: Intended Audience :: Developers
Classifier: Programming Language :: Python :: 3.9
Classifier: Operating System :: Microsoft :: Windows
Classifier: Operating System :: POSIX :: Linux
